betacaptcha/__init__.py
betacaptcha/main.py
betacaptcha-0.3.0.dist-info/METADATA
betacaptcha-0.3.0.dist-info/WHEEL
betacaptcha-0.3.0.dist-info/top_level.txt
betacaptcha-0.3.0.dist-info/RECORD
