Metadata-Version: 2.1
Name: betacaptcha
Version: 0.3.0
Author: Than Tuan Bao
Author-email: thantuanbao66@gmail.com
Classifier: Programming Language :: Python :: 3
Classifier: License :: OSI Approved :: MIT License
Classifier: Operating System :: OS Independent
Requires-Python: >=3.6
